<?xml version='1.0' encoding='UTF-8'?>
<dataset>
<record><id>1</id><first_name>Vernon</first_name><last_name>Hamblington</last_name><email>vhamblington0@eepurl.com</email><gender>Male</gender><ip_address>197.84.38.69</ip_address></record><record><id>2</id><first_name>Abbey</first_name><last_name>Ponter</last_name><email>aponter1@sina.com.cn</email><gender>Male</gender><ip_address>88.225.216.204</ip_address></record><record><id>3</id><first_name>Madelyn</first_name><last_name>Couttes</last_name><email>mcouttes2@bloglines.com</email><gender>Female</gender><ip_address>134.42.85.128</ip_address></record><record><id>4</id><first_name>Tobiah</first_name><last_name>McGurgan</last_name><email>tmcgurgan3@mozilla.org</email><gender>Male</gender><ip_address>82.72.53.35</ip_address></record><record><id>5</id><first_name>Bo</first_name><last_name>Howlett</last_name><email>bhowlett4@ow.ly</email><gender>Male</gender><ip_address>185.115.30.135</ip_address></record><record><id>6</id><first_name>Grove</first_name><last_name>Tinklin</last_name><email>gtinklin5@telegraph.co.uk</email><gender>Male</gender><ip_address>192.52.236.54</ip_address></record><record><id>7</id><first_name>Marco</first_name><last_name>Trodd</last_name><email>mtrodd6@eepurl.com</email><gender>Male</gender><ip_address>24.51.113.55</ip_address></record><record><id>8</id><first_name>Urbain</first_name><last_name>Scrymgeour</last_name><email>uscrymgeour7@nhs.uk</email><gender>Male</gender><ip_address>100.130.169.232</ip_address></record><record><id>9</id><first_name>Ronnica</first_name><last_name>Sorbey</last_name><email>rsorbey8@zimbio.com</email><gender>Female</gender><ip_address>176.169.29.99</ip_address></record><record><id>10</id><first_name>Cly</first_name><last_name>Egdal</last_name><email>cegdal9@wikia.com</email><gender>Male</gender><ip_address>145.204.184.55</ip_address></record><record><id>11</id><first_name>Keelby</first_name><last_name>Styant</last_name><email>kstyanta@wisc.edu</email><gender>Male</gender><ip_address>162.28.74.33</ip_address></record><record><id>12</id><first_name>Blanche</first_name><last_name>Gringley</last_name><email>bgringleyb@phoca.cz</email><gender>Female</gender><ip_address>199.45.205.211</ip_address></record><record><id>13</id><first_name>Brennen</first_name><last_name>Hinksen</last_name><email>bhinksenc@msu.edu</email><gender>Male</gender><ip_address>171.99.247.9</ip_address></record><record><id>14</id><first_name>Tiff</first_name><last_name>Burberry</last_name><email>tburberryd@soup.io</email><gender>Female</gender><ip_address>148.148.169.130</ip_address></record><record><id>15</id><first_name>Aili</first_name><last_name>Mollene</last_name><email>amollenee@who.int</email><gender>Female</gender><ip_address>76.233.30.173</ip_address></record></dataset>